{
  "source": {
    "type": "github",
    "owner": "Dicklesworthstone",
    "repo": "beads_rust",
    "channel": "github-head",
    "defaultBranch": "main",
    "version": "0.2.5",
    "rev": "b7fa2ccf40c7e8fb6623bf70b71d9da09a113adb",
    "hash": "sha256-rUaNPlKi1TQBKEbV+cs2IvN0yUXUoZjmrbjtTuc+tlU=",
    "siblings": {
      "frankensqlite": {
        "owner": "Dicklesworthstone",
        "repo": "frankensqlite",
        "rev": "daf811cdae30c9f2078d17938ff0d4c63c37f933",
        "hash": "sha256-hN0WQNZTGiC55ALrfF5MnBjbXqbuRKFwQMJyfLLPUdE="
      }
    }
  },
  "package": {
    "repo": "beads-rust",
    "version": "0.2.5"
  },
  "binary": {
    "name": "br"
  },
  "meta": {
    "description": "Agent-first issue tracker",
    "homepage": "https://github.com/Dicklesworthstone/beads_rust",
    "licenseSpdx": "MIT"
  }
}
