{
  "source": {
    "type": "github",
    "owner": "Dicklesworthstone",
    "repo": "beads_rust",
    "channel": "github-head",
    "defaultBranch": "main",
    "version": "0.2.7",
    "rev": "a218dece947994a45f101202a07af9fe602be9ec",
    "hash": "sha256-rKOTrxJ/QdVy6x9XY96Y/ihQk5ItL8AgFXQk6a1ipBo=",
    "siblings": {
      "frankensqlite": {
        "owner": "Dicklesworthstone",
        "repo": "frankensqlite",
        "rev": "42cf056aca1d622e29077ff03e133b3fc249aef2",
        "hash": "sha256-c6usOR3CtNOBUgLUh6KiOG1rYWWMI7vtzVGJAfORcPk="
      }
    }
  },
  "package": {
    "repo": "beads-rust",
    "version": "0.2.7"
  },
  "binary": {
    "name": "br"
  },
  "meta": {
    "description": "Agent-first issue tracker",
    "homepage": "https://github.com/Dicklesworthstone/beads_rust",
    "licenseSpdx": "MIT"
  }
}
