{
  "source": {
    "type": "github",
    "owner": "Dicklesworthstone",
    "repo": "beads_rust",
    "channel": "github-head",
    "defaultBranch": "main",
    "version": "0.2.10",
    "rev": "18d1c285a99ced522471bc1d11ee27a8d2cf79ba",
    "hash": "sha256-CndoL2tgPg4sU0cNcCE5IkuW1Y7VKbO7//zl9w1CdQA=",
    "siblings": {
      "frankensqlite": {
        "owner": "Dicklesworthstone",
        "repo": "frankensqlite",
        "rev": "15ce2f1b1d38faf52a10754e60d1e41049d13131",
        "hash": "sha256-nY0M9JzjNIOk+Wa1ICcd/bvUGlZaboP+nmIkNHWTczs="
      }
    }
  },
  "package": {
    "repo": "beads-rust",
    "version": "0.2.10"
  },
  "binary": {
    "name": "br"
  },
  "meta": {
    "description": "Agent-first issue tracker",
    "homepage": "https://github.com/Dicklesworthstone/beads_rust",
    "licenseSpdx": "MIT"
  }
}
