{
  "source": {
    "type": "github",
    "owner": "Dicklesworthstone",
    "repo": "beads_rust",
    "channel": "github-head",
    "defaultBranch": "main",
    "version": "0.2.1",
    "rev": "d4cd1c91789f89e5d1e31e069ef750633827baf4",
    "hash": "sha256-1LG2pwYLzFHjPq7amxRjW0dg1rViFOx0qVlA9chqimA=",
    "siblings": {
      "frankensqlite": {
        "owner": "Dicklesworthstone",
        "repo": "frankensqlite",
        "rev": "e5c83f116a48b45143cce5666081f245ed55172b",
        "hash": "sha256-TaxMGM0ki/3yhBpMAwL0GvZKj088c4Z0P/sapf+0rsw="
      }
    }
  },
  "package": {
    "repo": "beads-rust",
    "version": "0.2.1"
  },
  "binary": {
    "name": "br"
  },
  "meta": {
    "description": "Agent-first issue tracker",
    "homepage": "https://github.com/Dicklesworthstone/beads_rust",
    "licenseSpdx": "MIT"
  }
}
